{
  "name": "Milton Perkins",
  "age": 21,
  "address": {
    "street": "Cogrew Ridge",
    "city": "Gilanne",
    "state": "CT",
    "zip": "73892"
  },
  "contact": {
    "phone": "(742) 318-8543",
    "servicePhone": "800214827"
  },
  "birthday": "1965-09-05T11:19:24.095Z",
  "ip": "70.209.2.58",
  "foo": "bar",
  "profile": {
    "about": "Leoview nudzalev raz wi pohara eheuv bife levujjom lurziw laboala za wiv nof ninan cancagi har gaw. Meppaopo zuruop homo bedubi jibjodic niplifzus bejpez reg cehmul ete oni zur zu evfehbup. Jubes duuhe nowmonmi oda bap sivpu nogizcog hav dag gupucteh cuczum hi leog boofirin. Lubzawbe mog patpo jamkafe ozaamgem deaddo ikupikis to iwkirzo ah kifa awecij. De mene tut migtuos begeja ofikazi zakentuc ec vesmu rig junmiw vembo. Os apo apu ehakew iboapi rimunok wipezec cod tu car wu vada izcora. Pal ufo wew varcoze ifi fomnul futo af li kiznof abemucba medkoabo rihadmow wessa ne guke opgucbed evorru.",
    "bio": "Ez be kac zaj eccu fomecacu nureh cuvbufu kuug potpa suzku we vud ujeleg livero wi jo. Elkacwi uc pimior dultu ra isoirzo haj tucob amibupi cuz juku dewamkeg. Ura opi zeevuic tol facpacdit cegsa cadti avila uzwo cab vu ow nivdi."
  },
  "apiKey": "7b4e62840fd65b806f856aae6afb613b456bc77b76605c9d0bb7103dc7bb5c91",
  "currency": {
    "code": "BSD",
    "name": "Bahamas Dollar"
  }
}